dependence/__init__.py
dependence/control_folder_exist.py
dependence/function_read.py
dependence/function_write.py
utils/DataIO.py
utils/__init__.py
rw_dataframe_data_io-0.1.4.dist-info/LICENSE.txt
rw_dataframe_data_io-0.1.4.dist-info/METADATA
rw_dataframe_data_io-0.1.4.dist-info/WHEEL
rw_dataframe_data_io-0.1.4.dist-info/entry_points.txt
rw_dataframe_data_io-0.1.4.dist-info/top_level.txt
rw_dataframe_data_io-0.1.4.dist-info/RECORD
