Metadata-Version: 2.1
Name: rw-dataframe-data-io
Version: 0.1.4
Summary: A function to read or write data to a file. Supports CSV, JSON, and Pickle file formats.
Home-page: https://github.com/dicesare/data_io.git
Author: antony coco
Author-email: antony.coco.pro@gmail.com
Classifier: Programming Language :: Python :: 3
Classifier: License :: OSI Approved :: MIT License
Classifier: Operating System :: OS Independent
Requires-Python: >=3.8
License-File: LICENSE.txt
Requires-Dist: pandas (>=1.3.0)
Requires-Dist: numpy (>=1.23.0)
Requires-Dist: pathlib (>=1.0.0)
Requires-Dist: setuptools (>=67.6.1)
